opt_sugar/__init__.py
opt_sugar/extra_sugar/__init__.py
opt_sugar/extra_sugar/extra_sugar.py
opt_sugar/extra_sugar/objective.py
opt_sugar/low_sugar/__init__.py
opt_sugar/low_sugar/low_sugar.py
opt_sugar/opt_flow/__init__.py
opt_sugar/opt_flow/pyfunc.py
opt_sugar-0.0.4.9.dist-info/LICENSE.txt
opt_sugar-0.0.4.9.dist-info/METADATA
opt_sugar-0.0.4.9.dist-info/WHEEL
opt_sugar-0.0.4.9.dist-info/top_level.txt
opt_sugar-0.0.4.9.dist-info/RECORD
