Metadata-Version: 2.1
Name: opt-sugar
Version: 0.0.4.9
Home-page: https://github.com/juandados/opt-sugar
Author: Juan Chacon
Author-email: juandados@gmail.com
Keywords: optimization operations mathematical programming
License-File: LICENSE.txt
Requires-Dist: numpy
Requires-Dist: gurobipy
Requires-Dist: scikit-learn
